susyapi/__init__.py
susyapi-0.1.1.dist-info/LICENSE
susyapi-0.1.1.dist-info/METADATA
susyapi-0.1.1.dist-info/WHEEL
susyapi-0.1.1.dist-info/top_level.txt
susyapi-0.1.1.dist-info/RECORD
