Metadata-Version: 2.1
Name: susyapi
Version: 0.1.1
Summary: An API for getting information from University of Campinas' Submission System
Home-page: https://github.com/IvanIsCoding/SuSyAPI
Author: Ivan Carvalho
Author-email: ivan.carvalho@alumni.ubc.ca
License: MIT
Keywords: unicamp susy api
Platform: UNKNOWN
Classifier: Development Status :: 3 - Alpha
Classifier: Intended Audience :: Developers
Classifier: Topic :: Software Development :: Build Tools
Classifier: License :: OSI Approved :: MIT License
Classifier: Programming Language :: Python :: 3
Classifier: Programming Language :: Python :: 3.5
Classifier: Programming Language :: Python :: 3.6
Classifier: Programming Language :: Python :: 3.7
Requires-Python: >=3.5
Requires-Dist: bs4
Requires-Dist: requests
